ssh_mcp_server/__init__.py
ssh_mcp_server/__main__.py
ssh_mcp_server/server.py
mcp_ssh_server-0.1.4.dist-info/METADATA
mcp_ssh_server-0.1.4.dist-info/WHEEL
mcp_ssh_server-0.1.4.dist-info/entry_points.txt
mcp_ssh_server-0.1.4.dist-info/licenses/LICENSE
mcp_ssh_server-0.1.4.dist-info/RECORD
