Metadata-Version: 2.4
Name: mcp-ssh-server
Version: 0.1.4
Summary: SSH MCP Server - 基于 Model Context Protocol 的 SSH 连接管理和命令执行服务器
Project-URL: Homepage, https://github.com/liang04/ssh-mcp
Project-URL: Repository, https://github.com/liang04/ssh-mcp
Project-URL: Issues, https://github.com/liang04/ssh-mcp/issues
Author-email: liang04 <liang04@users.noreply.github.com>
License: MIT
License-File: LICENSE
Keywords: command,mcp,model-context-protocol,remote,sftp,ssh
Classifier: Development Status :: 4 - Beta
Classifier: Intended Audience :: Developers
Classifier: License :: OSI Approved :: MIT License
Classifier: Operating System :: OS Independent
Classifier: Programming Language :: Python :: 3
Classifier: Programming Language :: Python :: 3.10
Classifier: Programming Language :: Python :: 3.11
Classifier: Programming Language :: Python :: 3.12
Classifier: Topic :: System :: Networking
Classifier: Topic :: System :: Systems Administration
Requires-Python: >=3.10
Requires-Dist: mcp>=1.0.0
Requires-Dist: paramiko>=3.0.0
